django_htpy/__init__.py
django_htpy/apps.py
django_htpy/renderable.py
django_htpy/templatetags/__init__.py
django_htpy/templatetags/htpy.py
django_htpy-25.1.dist-info/LICENSE
django_htpy-25.1.dist-info/WHEEL
django_htpy-25.1.dist-info/METADATA
django_htpy-25.1.dist-info/RECORD
