Metadata-Version: 2.1
Name: django-htpy
Version: 25.1
Summary: django-htpy: Django specific add-ons for the htpy library.
Author-email: Carlton Gibson <carlton.gibson@noumenal.es>
Classifier: License :: OSI Approved :: MIT License
Requires-Dist: django
Requires-Dist: htpy
Project-URL: Home, https://noumenal.es/django-htpy/
